LICENSE
MANIFEST.in
README.md
setup.py
nexosisapi/__init__.py
nexosisapi/algorithm.py
nexosisapi/algorithm_contestant.py
nexosisapi/anomaly_distances.py
nexosisapi/anomaly_scores.py
nexosisapi/calendar_join.py
nexosisapi/class_scores.py
nexosisapi/column_metadata.py
nexosisapi/column_options.py
nexosisapi/confusion_matrix.py
nexosisapi/data_source_type.py
nexosisapi/dataset.py
nexosisapi/dataset_join.py
nexosisapi/dataset_summary.py
nexosisapi/distance_metric.py
nexosisapi/feature_importance.py
nexosisapi/import_response.py
nexosisapi/join.py
nexosisapi/link.py
nexosisapi/list_queries.py
nexosisapi/model_summary.py
nexosisapi/outlier.py
nexosisapi/paged_list.py
nexosisapi/session.py
nexosisapi/session_contest.py
nexosisapi/session_selection_metrics.py
nexosisapi/sort_order.py
nexosisapi/status.py
nexosisapi/time_interval.py
nexosisapi/timeseries_outliers.py
nexosisapi/view_definition.py
nexosisapi/vocabulary.py
nexosisapi/vocabulary_summary.py
nexosisapi/word.py
nexosisapi.egg-info/PKG-INFO
nexosisapi.egg-info/SOURCES.txt
nexosisapi.egg-info/dependency_links.txt
nexosisapi.egg-info/not-zip-safe
nexosisapi.egg-info/requires.txt
nexosisapi.egg-info/top_level.txt
nexosisapi/client/__init__.py
nexosisapi/client/client.py
nexosisapi/client/client_error.py
nexosisapi/client/datasets.py
nexosisapi/client/http_client.py
nexosisapi/client/imports.py
nexosisapi/client/models.py
nexosisapi/client/sessions.py
nexosisapi/client/views.py
nexosisapi/client/vocabularies.py
nexosisapi/tests/__init__.py
nexosisapi/tests/fake_http_client.py
nexosisapi/tests/test_basic.py
nexosisapi/tests/test_contest.py
nexosisapi/tests/test_contest_integration.py
nexosisapi/tests/test_datasets_integration.py
nexosisapi/tests/test_import.py
nexosisapi/tests/test_import_integration.py
nexosisapi/tests/test_list_queries.py
nexosisapi/tests/test_model_integration.py
nexosisapi/tests/test_model_operations.py
nexosisapi/tests/test_session.py
nexosisapi/tests/test_session_integration.py
nexosisapi/tests/test_view_integration.py
nexosisapi/tests/test_view_model.py
nexosisapi/tests/test_vocabulary.py
nexosisapi/tests/test_vocabulary_integration.py